lambdawaker/dataset/DataProvider.py
lambdawaker/dataset/Dataset.py
lambdawaker/dataset/DiskDataset.py
lambdawaker/dataset/DiskProvider.py
lambdawaker/dataset/FieldCaster.py
lambdawaker/dataset/ImageSequence.py
lambdawaker/dataset/Record.py
lambdawaker/dataset/hadlers/DatasetSourceHandler.py
lambdawaker/dataset/hadlers/HfDatasetSource.py
lambdawaker/dataset/hadlers/__init__.py
lambdawaker/dataset/hadlers/process_data_payload.py
lambdawaker/draw/test10.py
lambdawaker/draw/test4.py
lambdawaker/draw/test9.py
lambdawaker/draw/card_background/__init__.py
lambdawaker/draw/card_background/type_a.py
lambdawaker/draw/card_background/type_b.py
lambdawaker/draw/card_background/type_c.py
lambdawaker/draw/card_background/type_d.py
lambdawaker/draw/color/HSLuvColor.py
lambdawaker/draw/color/__init__.py
lambdawaker/draw/color/generate_color.py
lambdawaker/draw/color/generate_from_color.py
lambdawaker/draw/color/utils.py
lambdawaker/draw/color/visualization.py
lambdawaker/draw/credit_card/__init__.py
lambdawaker/draw/credit_card/chip_generator.py
lambdawaker/draw/gradient/__init__.py
lambdawaker/draw/gradient/linear_gradient/__init__.py
lambdawaker/draw/gradient/linear_gradient/create.py
lambdawaker/draw/gradient/linear_gradient/paint.py
lambdawaker/draw/gradient/linear_gradient/parameters.py
lambdawaker/draw/gradient/radial_gradient/__init__.py
lambdawaker/draw/gradient/radial_gradient/create.py
lambdawaker/draw/gradient/radial_gradient/paint.py
lambdawaker/draw/gradient/radial_gradient/parameters.py
lambdawaker/draw/gradient/sin/__init__.py
lambdawaker/draw/gradient/sin/create.py
lambdawaker/draw/gradient/sin/paint.py
lambdawaker/draw/gradient/sin/parameters.py
lambdawaker/draw/gradient/voronoid/__init__.py
lambdawaker/draw/gradient/voronoid/create.py
lambdawaker/draw/gradient/voronoid/paint.py
lambdawaker/draw/gradient/voronoid/parameters.py
lambdawaker/draw/grid/__init__.py
lambdawaker/draw/grid/concentric_polygons/__init__.py
lambdawaker/draw/grid/concentric_polygons/create.py
lambdawaker_draw_tools-0.2.32.dist-info/licenses/LICENSE
lambdawaker_draw_tools-0.2.32.dist-info/METADATA
lambdawaker_draw_tools-0.2.32.dist-info/WHEEL
lambdawaker_draw_tools-0.2.32.dist-info/top_level.txt
lambdawaker_draw_tools-0.2.32.dist-info/RECORD
