Metadata-Version: 2.4
Name: lambdawaker.draw.tools
Version: 0.2.32
Summary: Drawing utilities for generating geometric patterns and grids using Pillow and aggdraw
Author-email: LambdaWalker <lambdawaker@isdavid.com>
Project-URL: Homepage, https://github.com/lambdawalker/python_lw_drawing_tools
Project-URL: Repository, https://github.com/lambdawalker/python_lw_drawing_tools
Project-URL: Issues, https://github.com/lambdawalker/python_lw_drawing_tools/issues
Keywords: graphics,drawing,pillow,aggdraw,geometry,grid,patterns
Classifier: Intended Audience :: Developers
Classifier: Programming Language :: Python :: 3
Classifier: Programming Language :: Python :: 3 :: Only
Classifier: Topic :: Multimedia :: Graphics
Requires-Python: >=3.8
License-File: LICENSE
Requires-Dist: Pillow>=12.0.0
Requires-Dist: aggdraw==1.4.1
Requires-Dist: numpy>=2.2.6
Requires-Dist: hsluv==5.0.4
Requires-Dist: jinja2==3.1.6
Requires-Dist: cairosvg==2.8.2
Requires-Dist: tqdm==4.67.1
Requires-Dist: playwright==1.57.0
Requires-Dist: fastapi==0.128.0
Requires-Dist: moderngl==5.12.0
Requires-Dist: rich==14.3.1
Requires-Dist: starlette==0.50.0
Requires-Dist: noise==1.2.2
Requires-Dist: datasets==4.5.0
Requires-Dist: requests==2.32.5
Requires-Dist: uvicorn==0.40.0
Dynamic: license-file
